mpscenes/__init__.py
mpscenes/common/__init__.py
mpscenes/common/analytic_trajectory.py
mpscenes/common/component.py
mpscenes/common/errors.py
mpscenes/common/reference_trajectory.py
mpscenes/common/spline_trajectory.py
mpscenes/goals/__init__.py
mpscenes/goals/dynamic_sub_goal.py
mpscenes/goals/goal_composition.py
mpscenes/goals/static_joint_space_sub_goal.py
mpscenes/goals/static_sub_goal.py
mpscenes/goals/sub_goal.py
mpscenes/goals/sub_goal_creator.py
mpscenes/obstacles/__init__.py
mpscenes/obstacles/box_obstacle.py
mpscenes/obstacles/box_smooth.mtl
mpscenes/obstacles/box_smooth.obj
mpscenes/obstacles/collision_obstacle.py
mpscenes/obstacles/cylinder_obstacle.py
mpscenes/obstacles/dynamic_box_obstacle.py
mpscenes/obstacles/dynamic_cylinder_obstacle.py
mpscenes/obstacles/dynamic_obstacle.py
mpscenes/obstacles/dynamic_sphere_obstacle.py
mpscenes/obstacles/dynamic_urdf_obstacle.py
mpscenes/obstacles/obstacleCreator.py
mpscenes/obstacles/sphere_obstacle.py
mpscenes/obstacles/sphere_smooth.mtl
mpscenes/obstacles/sphere_smooth.obj
mpscenes/obstacles/urdf_obstacle.py
mpscenes-0.4.6.dist-info/METADATA
mpscenes-0.4.6.dist-info/WHEEL
mpscenes-0.4.6.dist-info/RECORD
